[{"pk": 5, "model": "cluster.role", "fields": {"note": "", "updated_on": "2009-07-29 11:59:08", "created_on": "2009-07-29 11:59:08", "label": "admin node", "tags": ""}}, {"pk": 1, "model": "cluster.role", "fields": {"note": "", "updated_on": "2009-07-29 11:58:24", "created_on": "2009-07-29 11:57:42", "label": "compute node", "tags": ""}}, {"pk": 8, "model": "cluster.role", "fields": {"note": "", "updated_on": "2009-07-29 12:01:05", "created_on": "2009-07-29 12:01:05", "label": "database server", "tags": ""}}, {"pk": 9, "model": "cluster.role", "fields": {"note": "", "updated_on": "2009-07-29 12:03:16", "created_on": "2009-07-29 12:03:16", "label": "ldap server", "tags": ""}}, {"pk": 6, "model": "cluster.role", "fields": {"note": "", "updated_on": "2009-07-29 11:59:12", "created_on": "2009-07-29 11:59:12", "label": "login node", "tags": ""}}, {"pk": 3, "model": "cluster.role", "fields": {"note": "", "updated_on": "2009-07-29 11:58:43", "created_on": "2009-07-29 11:58:43", "label": "patchpanel", "tags": ""}}, {"pk": 4, "model": "cluster.role", "fields": {"note": "", "updated_on": "2009-07-29 11:59:04", "created_on": "2009-07-29 11:59:04", "label": "pdu", "tags": ""}}, {"pk": 10, "model": "cluster.role", "fields": {"note": "", "updated_on": "2009-07-29 12:03:42", "created_on": "2009-07-29 12:03:42", "label": "project server", "tags": ""}}, {"pk": 2, "model": "cluster.role", "fields": {"note": "", "updated_on": "2009-07-29 11:57:46", "created_on": "2009-07-29 11:57:46", "label": "switch", "tags": ""}}, {"pk": 7, "model": "cluster.role", "fields": {"note": "", "updated_on": "2009-07-29 12:00:40", "created_on": "2009-07-29 12:00:40", "label": "wiki server", "tags": ""}}]
